irl_maxent/__init__.py
irl_maxent/gridworld.py
irl_maxent/maxent.py
irl_maxent/optimizer.py
irl_maxent/plot.py
irl_maxent/solver.py
irl_maxent/test_gridworld.py
irl_maxent/trajectory.py
irl_maxent-0.1.0.dist-info/LICENSE
irl_maxent-0.1.0.dist-info/METADATA
irl_maxent-0.1.0.dist-info/WHEEL
irl_maxent-0.1.0.dist-info/top_level.txt
irl_maxent-0.1.0.dist-info/RECORD
