Metadata-Version: 2.1
Name: irl-maxent
Version: 0.1.0
Summary: A small package for Maximum Entropy Inverse Reinforcement Learning on simple MDPs
Home-page: https://github.com/qzed/irl-maxent
Author: Maximilian Luz
Author-email: luzmaximilian@gmail.com
License: UNKNOWN
Project-URL: Bug Tracker, https://github.com/qzed/irl-maxent/issues
Platform: UNKNOWN
Classifier: Programming Language :: Python :: 3
Classifier: License :: OSI Approved :: MIT License
Classifier: Operating System :: OS Independent
Requires-Python: >=3.6
License-File: LICENSE
Requires-Dist: numpy
Requires-Dist: matplotlib
